binance_spot/__init__.py
binance_spot/api_client.py
binance_spot/configuration.py
binance_spot/rest.py
binance_spot/api/__init__.py
binance_spot/api/auto_invest_api.py
binance_spot/api/b_swap_api.py
binance_spot/api/blvt_api.py
binance_spot/api/c2_c_api.py
binance_spot/api/convert_api.py
binance_spot/api/crypto_loans_api.py
binance_spot/api/fiat_api.py
binance_spot/api/futures_algo_api.py
binance_spot/api/futures_api.py
binance_spot/api/gift_card_api.py
binance_spot/api/isolated_margin_stream_api.py
binance_spot/api/margin_api.py
binance_spot/api/margin_stream_api.py
binance_spot/api/market_api.py
binance_spot/api/mining_api.py
binance_spot/api/nft_api.py
binance_spot/api/pay_api.py
binance_spot/api/portfolio_margin_api.py
binance_spot/api/rebate_api.py
binance_spot/api/savings_api.py
binance_spot/api/simple_earn_api.py
binance_spot/api/spot_algo_api.py
binance_spot/api/staking_api.py
binance_spot/api/stream_api.py
binance_spot/api/sub_account_api.py
binance_spot/api/trade_api.py
binance_spot/api/vip_loans_api.py
binance_spot/api/wallet_api.py
binance_spot/models/__init__.py
binance_spot/models/account.py
binance_spot/models/account_balances.py
binance_spot/models/account_commission_rates.py
binance_spot/models/agg_trade.py
binance_spot/models/apiv3all_order_list_orders.py
binance_spot/models/apiv3open_order_list_orders.py
binance_spot/models/bnb_burn_status.py
binance_spot/models/book_ticker.py
binance_spot/models/book_ticker_list.py
binance_spot/models/bswap_add_liquidity_preview_combination.py
binance_spot/models/bswap_add_liquidity_preview_single.py
binance_spot/models/bswap_rmv_liquidity_preview_combination.py
binance_spot/models/bswap_rmv_liquidity_preview_single.py
binance_spot/models/canceled_margin_order_detail.py
binance_spot/models/details.py
binance_spot/models/details1.py
binance_spot/models/details2.py
binance_spot/models/error.py
binance_spot/models/inline_response200.py
binance_spot/models/inline_response2001.py
binance_spot_sdk-0.0.2.dist-info/LICENSE
binance_spot_sdk-0.0.2.dist-info/METADATA
binance_spot_sdk-0.0.2.dist-info/WHEEL
binance_spot_sdk-0.0.2.dist-info/top_level.txt
binance_spot_sdk-0.0.2.dist-info/RECORD
