Metadata-Version: 2.1
Name: binance-spot-sdk
Version: 0.0.2
Summary: A SDK for Binance Public Spot API
Home-page: https://github.com/Halimao/binance-spot-sdk
Author-email: halimao.lin@gmail.com
Keywords: Binance Public Spot API
License-File: LICENSE
Requires-Dist: urllib3 >=1.15
Requires-Dist: six >=1.10
Requires-Dist: certifi
Requires-Dist: python-dateutil
